qiskit_jku_provider-1.0.1.data/purelib/qiskit_jku_provider/CMakeCache.txt
qiskit_jku_provider-1.0.1.data/purelib/qiskit_jku_provider/Makefile
qiskit_jku_provider-1.0.1.data/purelib/qiskit_jku_provider/VERSION.txt
qiskit_jku_provider-1.0.1.data/purelib/qiskit_jku_provider/__init__.py
qiskit_jku_provider-1.0.1.data/purelib/qiskit_jku_provider/cmake_install.cmake
qiskit_jku_provider-1.0.1.data/purelib/qiskit_jku_provider/jku_simulator
qiskit_jku_provider-1.0.1.data/purelib/qiskit_jku_provider/jkujob.py
qiskit_jku_provider-1.0.1.data/purelib/qiskit_jku_provider/jkuprovider.py
qiskit_jku_provider-1.0.1.data/purelib/qiskit_jku_provider/jkusimulatorerror.py
qiskit_jku_provider-1.0.1.data/purelib/qiskit_jku_provider/qasm_simulator_jku.py
qiskit_jku_provider-1.0.1.data/purelib/qiskit_jku_provider/CMakeFiles/CMakeDirectoryInformation.cmake
qiskit_jku_provider-1.0.1.data/purelib/qiskit_jku_provider/CMakeFiles/CMakeOutput.log
qiskit_jku_provider-1.0.1.data/purelib/qiskit_jku_provider/CMakeFiles/Makefile.cmake
qiskit_jku_provider-1.0.1.data/purelib/qiskit_jku_provider/CMakeFiles/Makefile2
qiskit_jku_provider-1.0.1.data/purelib/qiskit_jku_provider/CMakeFiles/TargetDirectories.txt
qiskit_jku_provider-1.0.1.data/purelib/qiskit_jku_provider/CMakeFiles/cmake.check_cache
qiskit_jku_provider-1.0.1.data/purelib/qiskit_jku_provider/CMakeFiles/feature_tests.bin
qiskit_jku_provider-1.0.1.data/purelib/qiskit_jku_provider/CMakeFiles/feature_tests.cxx
qiskit_jku_provider-1.0.1.data/purelib/qiskit_jku_provider/CMakeFiles/progress.marks
qiskit_jku_provider-1.0.1.data/purelib/qiskit_jku_provider/CMakeFiles/3.12.3/CMakeCXXCompiler.cmake
qiskit_jku_provider-1.0.1.data/purelib/qiskit_jku_provider/CMakeFiles/3.12.3/CMakeDetermineCompilerABI_CXX.bin
qiskit_jku_provider-1.0.1.data/purelib/qiskit_jku_provider/CMakeFiles/3.12.3/CMakeSystem.cmake
qiskit_jku_provider-1.0.1.data/purelib/qiskit_jku_provider/CMakeFiles/3.12.3/CompilerIdCXX/CMakeCXXCompilerId.cpp
qiskit_jku_provider-1.0.1.dist-info/LICENSE
qiskit_jku_provider-1.0.1.dist-info/METADATA
qiskit_jku_provider-1.0.1.dist-info/WHEEL
qiskit_jku_provider-1.0.1.dist-info/top_level.txt
qiskit_jku_provider-1.0.1.dist-info/RECORD
